fiftyl_toolkit/__init__.py
fiftyl_toolkit/channelmaps.py
fiftyl_toolkit/wibethreader.py
fiftyl_toolkit-0.2.2.dist-info/LICENSE
fiftyl_toolkit-0.2.2.dist-info/WHEEL
fiftyl_toolkit-0.2.2.dist-info/METADATA
fiftyl_toolkit-0.2.2.dist-info/RECORD
