Metadata-Version: 2.3
Name: fiftyl_toolkit
Version: 0.2.2
Summary: 50L data toolkit
Author-email: Alejandro Oranday <alejandro@oran.day>
Requires-Python: >=3.10
Classifier: Programming Language :: Python :: 3
Classifier: License :: OSI Approved :: MIT License
Classifier: Intended Audience :: Science/Research
Requires-Dist: numpy
Project-URL: Home, https://github.com/aeoranday/fiftyl_toolkit
